bluetooth_adapters/__init__.py
bluetooth_adapters/adapters.py
bluetooth_adapters/const.py
bluetooth_adapters/dbus.py
bluetooth_adapters/history.py
bluetooth_adapters/mac_lookup.py
bluetooth_adapters/models.py
bluetooth_adapters/py.typed
bluetooth_adapters/storage.py
bluetooth_adapters/systems/__init__.py
bluetooth_adapters/systems/linux.py
bluetooth_adapters/systems/linux_hci.py
bluetooth_adapters/systems/macos.py
bluetooth_adapters/systems/windows.py
bluetooth_adapters/util.py
bluetooth_adapters-2.1.0.dist-info/LICENSE
bluetooth_adapters-2.1.0.dist-info/METADATA
bluetooth_adapters-2.1.0.dist-info/WHEEL
bluetooth_adapters-2.1.0.dist-info/RECORD
