Metadata-Version: 2.3
Name: bluetooth-adapters
Version: 2.1.0
Summary: Tools to enumerate and find Bluetooth Adapters
License: Apache-2.0
Author: J. Nick Koston
Author-email: nick@koston.org
Requires-Python: >=3.9
Classifier: Development Status :: 2 - Pre-Alpha
Classifier: Intended Audience :: Developers
Classifier: License :: OSI Approved :: Apache Software License
Classifier: Natural Language :: English
Classifier: Operating System :: OS Independent
Classifier: Programming Language :: Python :: 3
Classifier: Programming Language :: Python :: 3.9
Classifier: Programming Language :: Python :: 3.10
Classifier: Programming Language :: Python :: 3.11
Classifier: Programming Language :: Python :: 3.12
Classifier: Programming Language :: Python :: 3.13
Classifier: Topic :: Software Development :: Libraries
Provides-Extra: docs
Requires-Dist: Sphinx (>=5,<8) ; extra == "docs"
Requires-Dist: aiooui (>=0.1.1)
Requires-Dist: async-timeout (>=3.0.0) ; python_version < "3.11"
Requires-Dist: bleak (>=1)
Requires-Dist: dbus-fast (>=1.21.0) ; platform_system == "Linux"
Requires-Dist: myst-parser (>=0.18,<3.1) ; extra == "docs"
Requires-Dist: sphinx-rtd-theme (>=1,<4) ; extra == "docs"
Requires-Dist: uart-devices (>=0.1.0)
Requires-Dist: usb-devices (>=0.4.5)
Project-URL: Bug Tracker, https://github.com/bluetooth-devices/bluetooth-adapters/issues
Project-URL: Changelog, https://github.com/bluetooth-devices/bluetooth-adapters/blob/main/CHANGELOG.md
Project-URL: Documentation, https://bluetooth-adapters.readthedocs.io
Project-URL: Repository, https://github.com/bluetooth-devices/bluetooth-adapters
